sodukusolver/__init__.py
sodukusolver/server.py
sodukusolver/solver.py
mseep_sodukusolver-0.1.1.dist-info/METADATA
mseep_sodukusolver-0.1.1.dist-info/WHEEL
mseep_sodukusolver-0.1.1.dist-info/entry_points.txt
mseep_sodukusolver-0.1.1.dist-info/top_level.txt
mseep_sodukusolver-0.1.1.dist-info/RECORD
