Metadata-Version: 2.4
Name: mseep-sodukusolver
Version: 0.1.1
Summary: A MCP server project
Author-email: mseep <support@skydeck.ai>
Requires-Python: >=3.10
Requires-Dist: mcp>=1.4.1
